{
  "appPageId" : "6f87ce43-8103-412d-b337-9119174263c8",
  "componentName" : "siteforce:sldsOneColLayout",
  "dataProviders" : [ ],
  "id" : "0563ac0e-d276-4666-a7f5-39f9f5f01763",
  "label" : "Action Plan Template Detail",
  "regions" : [ {
    "components" : [ {
      "componentAttributes" : { },
      "componentName" : "runtime_industries_actionplan:highlightsPanel",
      "id" : "9836b1b1-f7c2-49c1-b208-fae45cd9e5d9",
      "renderPriority" : "NEUTRAL",
      "renditionMap" : { },
      "type" : "component"
    } ],
    "id" : "7880c9ec-793a-48f3-b0fa-678c2927ccf7",
    "regionName" : "header",
    "type" : "region"
  }, {
    "components" : [ {
      "componentAttributes" : {
        "tabsetConfig" : {
          "UUID" : "7213c3c7-321d-4069-b559-7d29329ac06f",
          "activeTab" : "tab1",
          "tabs" : [ {
            "UUID" : "deed15d2-ea56-4f8f-8beb-99f2bdc8d48b",
            "allowGuestUser" : false,
            "locked" : false,
            "seedComponents" : [ {
              "attributes" : { },
              "fqn" : "runtime_industries_actionplan:taskManager"
            }, {
              "attributes" : { },
              "fqn" : "runtime_industries_actionplan:checklistItemManager"
            } ],
            "tabKey" : "tab1",
            "tabName" : "Items"
          }, {
            "UUID" : "b14d2383-b473-437e-abf4-bdb2d6b29df9",
            "allowGuestUser" : false,
            "locked" : false,
            "seedComponents" : [ {
              "attributes" : { },
              "fqn" : "forceCommunity:recordDetail"
            } ],
            "tabKey" : "tab2",
            "tabName" : "Details"
          } ],
          "useOverflowMenu" : false
        }
      },
      "componentName" : "forceCommunity:tabLayout",
      "id" : "7213c3c7-321d-4069-b559-7d29329ac06f",
      "regions" : [ {
        "components" : [ {
          "componentAttributes" : {
            "fieldSelection" : [ ]
          },
          "componentName" : "runtime_industries_actionplan:taskManager",
          "id" : "2e7de6cb-4017-439e-bb14-880712d0964a",
          "renderPriority" : "NEUTRAL",
          "renditionMap" : { },
          "type" : "component"
        }, {
          "componentAttributes" : { },
          "componentName" : "runtime_industries_actionplan:checklistItemManager",
          "id" : "7d9f7cb5-72ec-4574-84b1-aee46443ba68",
          "renderPriority" : "NEUTRAL",
          "renditionMap" : { },
          "type" : "component"
        } ],
        "id" : "deed15d2-ea56-4f8f-8beb-99f2bdc8d48b",
        "regionLabel" : "Items",
        "regionName" : "tab1",
        "renditionMap" : { },
        "type" : "region"
      }, {
        "components" : [ {
          "componentAttributes" : {
            "recordId" : "{!recordId}"
          },
          "componentName" : "forceCommunity:recordDetail",
          "id" : "1c8a7271-aae8-4469-bfaa-096c58f06bcd",
          "renderPriority" : "NEUTRAL",
          "renditionMap" : { },
          "type" : "component"
        } ],
        "id" : "b14d2383-b473-437e-abf4-bdb2d6b29df9",
        "regionLabel" : "Details",
        "regionName" : "tab2",
        "renditionMap" : { },
        "type" : "region"
      } ],
      "renderPriority" : "NEUTRAL",
      "renditionMap" : { },
      "type" : "component"
    } ],
    "id" : "a121c9b8-719f-4c36-ae20-9fbd6125d94f",
    "regionName" : "content",
    "type" : "region"
  }, {
    "id" : "8b481aa5-57b9-4b62-8f01-50a11a92befc",
    "regionName" : "footer",
    "type" : "region"
  }, {
    "components" : [ {
      "componentAttributes" : {
        "customHeadTags" : "",
        "description" : "",
        "title" : "{!Record._Object}: {!Record._Title}"
      },
      "componentName" : "forceCommunity:seoAssistant",
      "id" : "ba1c6f55-eac3-4372-b776-a163a24f6493",
      "renditionMap" : { },
      "type" : "component"
    } ],
    "id" : "33f12d7b-afa6-4e6a-b452-e6ccb8194fe1",
    "regionName" : "sfdcHiddenRegion",
    "type" : "region"
  } ],
  "themeLayoutType" : "Inner",
  "type" : "view",
  "viewType" : "detail-0PR"
}