{
  "appPageId" : "09e90440-dbed-4496-b14c-1a294d7bc2e4",
  "componentName" : "siteforce:sldsOneColLayout",
  "dataProviders" : [ ],
  "id" : "82035444-6047-40ea-85fa-2081e1fd3ddb",
  "label" : "HomeUplift",
  "regions" : [ {
    "id" : "e5d60913-cee2-4ad5-826f-3e8ef0d6da5e",
    "regionName" : "header",
    "type" : "region"
  }, {
    "components" : [ {
      "componentAttributes" : { },
      "componentName" : "c:myNetworkCaseList",
      "id" : "874ef031-71a3-4a67-b357-c770792821f9",
      "renderPriority" : "NEUTRAL",
      "renditionMap" : { },
      "type" : "component"
    } ],
    "id" : "1cfd58e5-489e-4c8c-a872-971f5a64e996",
    "regionName" : "content",
    "type" : "region"
  }, {
    "id" : "91cedf49-570d-4562-8f6b-a3fbeea49278",
    "regionName" : "footer",
    "type" : "region"
  }, {
    "components" : [ {
      "componentAttributes" : {
        "customHeadTags" : "",
        "description" : "",
        "title" : "Home"
      },
      "componentName" : "forceCommunity:seoAssistant",
      "id" : "d7ad297e-5d2c-4b9d-b6ed-e06291055e13",
      "renditionMap" : { },
      "type" : "component"
    } ],
    "id" : "5054c3f1-e9ce-4091-a7b9-972d3871ec02",
    "regionName" : "sfdcHiddenRegion",
    "type" : "region"
  } ],
  "themeLayoutType" : "Inner",
  "type" : "view",
  "viewType" : "home"
}